querify/__init__.py
querify/database/__init__.py
querify/database/client.py
querify/exceptions.py
querify/query.py
querify/sources/__init__.py
querify/sources/base_source.py
querify/sources/clients/__init__.py
querify/sources/clients/process.py
querify/sources/clients/storage.py
querify/sources/dirs.py
querify/sources/files.py
querify/sources/process.py
sql_querify-0.1.2.dist-info/LICENSE
sql_querify-0.1.2.dist-info/METADATA
sql_querify-0.1.2.dist-info/WHEEL
sql_querify-0.1.2.dist-info/entry_points.txt
sql_querify-0.1.2.dist-info/RECORD
